mlxploit/__init__.py
mlxploit/main.py
mlxploit-0.0.0.dist-info/METADATA
mlxploit-0.0.0.dist-info/WHEEL
mlxploit-0.0.0.dist-info/entry_points.txt
mlxploit-0.0.0.dist-info/RECORD
