Metadata-Version: 2.1
Name: mlxploit
Version: 0.0.0
Summary: An exploitation framework for AI/Machine Learning.
License: Apache-2.0
Author: hdks
Author-email: hdks.bug@gmail.com
Requires-Python: >=3.8,<4.0
Classifier: License :: OSI Approved :: Apache Software License
Classifier: Programming Language :: Python :: 3
Classifier: Programming Language :: Python :: 3.8
Classifier: Programming Language :: Python :: 3.9
Classifier: Programming Language :: Python :: 3.10
Classifier: Programming Language :: Python :: 3.11
Requires-Dist: typer[all] (>=0.9.0,<0.10.0)
